README.rst
setup.py
django_tint.egg-info/PKG-INFO
django_tint.egg-info/SOURCES.txt
django_tint.egg-info/dependency_links.txt
django_tint.egg-info/requires.txt
django_tint.egg-info/top_level.txt
tests/__init__.py
tests/settings.py
tests/tests_image_procs.py
tests/tests_models.py
tests/tests_tags.py
tests/tests_views.py
tests/urls.py
tint/__init__.py
tint/models.py
tint/settings.py
tint/urls.py
tint/views.py
tint/imageprocs/__init__.py
tint/imageprocs/default.py
tint/templatetags/__init__.py
tint/templatetags/tint.py